pytest_split_tests/__init__.py
picogrid_pytest_split_tests-2.0.0.dist-info/LICENSE
picogrid_pytest_split_tests-2.0.0.dist-info/METADATA
picogrid_pytest_split_tests-2.0.0.dist-info/WHEEL
picogrid_pytest_split_tests-2.0.0.dist-info/entry_points.txt
picogrid_pytest_split_tests-2.0.0.dist-info/top_level.txt
picogrid_pytest_split_tests-2.0.0.dist-info/RECORD
